nrp_client/__init__.py
nrp_client/docker_handle.py
nrp_client/nrp_server_docker_launchers.py
nrp_client/nrp_server_launchers.py
nrp_client-1.4.0.dist-info/METADATA
nrp_client-1.4.0.dist-info/WHEEL
nrp_client-1.4.0.dist-info/top_level.txt
nrp_client-1.4.0.dist-info/RECORD
